{
  "name": "Ma Source Beluga",
  "subtitle": "Apps & Plus",
  "description": "Bienvenue sur ma source personnalisée !",
  "iconURL": "https://imgur.com/a/tf4RK4Q",
  "website": "https://neocities.org",
  "tintColor": "#6156e2",
  "apps": [
    {
      "name": "Stremio Hacked",
      "bundleIdentifier": "com.stremio.ios",
      "developerName": "iOSGods",
      "subtitle": "Films et Séries",
      "localizedDescription": "Version modifiée de Stremio.",
      "iconURL": "https://imgur.com/a/tf4RK4Q",
      "tintColor": "#7a5af5",
      "category": "entertainment",
      "versions": [
        {
          "version": "2.0",
          "date": "2026-02-24T19:00:00+01:00",
          "downloadURL": "https://drive.google.com/uc?export=download&id=19sDYBxzqTn8Zb9vWjlIx9l58L-JqeY9Y",
          "size": 28900000,
          "buildVersion": "7",
          "minOSVersion": "12.0"
        }
      ]
    }
  ]
}
